satcube/__init__.py
satcube/_quiet.py
satcube/align.py
satcube/cloud.py
satcube/composite.py
satcube/config.py
satcube/download.py
satcube/exceptions.py
satcube/gapfill.py
satcube/interpolate.py
satcube/logging_config.py
satcube/objects.py
satcube/smooth.py
satcube/super.py
satcube/utils.py
satcube-0.1.32.dist-info/LICENSE
satcube-0.1.32.dist-info/METADATA
satcube-0.1.32.dist-info/WHEEL
satcube-0.1.32.dist-info/RECORD
