Metadata-Version: 2.1
Name: satcube
Version: 0.1.32
Summary: A Python package to create cloud-free monthly composites by fusing Landsat and Sentinel-2 data.
Home-page: https://github.com/IPL-UV/satcube
Author: Cesar Aybar
Author-email: fcesar.aybar@uv.es
Requires-Python: >=3.9
Classifier: Programming Language :: Python :: 3
Classifier: Programming Language :: Python :: 3.9
Classifier: Programming Language :: Python :: 3.10
Classifier: Programming Language :: Python :: 3.11
Classifier: Programming Language :: Python :: 3.12
Provides-Extra: full
Requires-Dist: cubexpress (==0.1.28)
Requires-Dist: mlstac (>=0.4.5)
Requires-Dist: phicloudmask (>=0.0.2)
Requires-Dist: requests (>=2.26.0)
Requires-Dist: satalign (==0.1.16)
Requires-Dist: scikit-learn (>=1.2.0)
Requires-Dist: segmentation-models-pytorch (>=0.3.0)
Requires-Dist: sen2sr (>=0.8.5)
Requires-Dist: torch (>=2.0.0) ; extra == "full"
Requires-Dist: tqdm (>=4.67.1)
Requires-Dist: xarray (>=2023.7.0)
Project-URL: Documentation, https://ipl-uv.github.io/satcube/
Project-URL: Repository, https://github.com/IPL-UV/satcube
